verple/__init__.py
verple/verple.py
verple/context/v1.0.0.jsonld
verple-1.0.0.dist-info/METADATA
verple-1.0.0.dist-info/WHEEL
verple-1.0.0.dist-info/licenses/LICENSE
verple-1.0.0.dist-info/RECORD
