Metadata-Version: 2.4
Name: verple
Version: 1.0.0
Summary: Verple is a ridiculously strict and ultra-conservative universal version format, comparator, serializer, and protocol.
Project-URL: Homepage, https://github.com/willynilly/verple
Project-URL: Documentation, https://github.com/willynilly/verple#readme
Project-URL: Issues, https://github.com/willynilly/verple/issues
Project-URL: Source, https://github.com/willynilly/verple
Author-email: Will Riley <wanderingwill@gmail.com>
License-Expression: Apache-2.0
License-File: LICENSE
Keywords: CalVer,PEP 440,SemVer,json-ld,linked data,pep440,provenance,semantic versioning,version parser,versioning
Classifier: Development Status :: 3 - Alpha
Classifier: Intended Audience :: Developers
Classifier: Intended Audience :: Education
Classifier: Intended Audience :: Information Technology
Classifier: Intended Audience :: Science/Research
Classifier: Intended Audience :: System Administrators
Classifier: License :: OSI Approved :: Apache Software License
Classifier: Natural Language :: English
Classifier: Operating System :: OS Independent
Classifier: Programming Language :: Python
Classifier: Programming Language :: Python :: 3
Classifier: Programming Language :: Python :: 3.10
Classifier: Programming Language :: Python :: 3.11
Classifier: Programming Language :: Python :: 3.12
Classifier: Programming Language :: Python :: 3.13
Classifier: Topic :: Scientific/Engineering
Classifier: Topic :: Scientific/Engineering :: Information Analysis
Classifier: Topic :: Software Development
Classifier: Topic :: Software Development :: Libraries :: Python Modules
Classifier: Topic :: Software Development :: Version Control
Classifier: Topic :: Utilities
Requires-Python: >=3.10
Requires-Dist: packaging>=25.0
Requires-Dist: semver>=3.0.4
Provides-Extra: dev
Requires-Dist: ruff>=0.11.12; extra == 'dev'
Provides-Extra: testing
Requires-Dist: pytest>=8.3.5; extra == 'testing'
